odacc/__init__.py
odacc/cli.py
tests/test_cli.py
oda_cc-0.1.9.dist-info/METADATA
oda_cc-0.1.9.dist-info/WHEEL
oda_cc-0.1.9.dist-info/entry_points.txt
oda_cc-0.1.9.dist-info/top_level.txt
oda_cc-0.1.9.dist-info/RECORD
