Metadata-Version: 2.1
Name: oda-cc
Version: 0.1.9
Summary: UNKNOWN
Home-page: http://packages.python.org/oda-cc
Author: Volodymyr Savchenko
Author-email: contact@volodymyrsavchenko.com
License: MIT
Keywords: oda
Platform: UNKNOWN
Classifier: Development Status :: 3 - Alpha
Classifier: Topic :: Utilities
Requires-Dist: click
